Assignment-2/A1/1-bit_ALU.v
/*
	K Rahul Reddy	17CO119
	Sushruth V	17CO148
	24 October 2018

	Op-Code : 4-bits
	bit 1 : neg_A
	bit 2 : neg_B
	bit 3,4 : indicate component
				00 => and
				01 => or
				10 => add

*/

module one_bit_ALU(output reg Result, output reg Zero, output reg CarryOut, input A, input B, input CarryIn, input[3:0] Op);
	reg a;
	reg b;
	always@(A, B, CarryIn, Op) begin
		a = (~A & Op[3]) | (A & ~Op[3]);
		b = (~B & Op[2]) | (B & ~Op[2]);
		if (Op[1:0] == 2'b00) begin
			Result = a & b;
		end
		if (Op[1:0] == 2'b01) begin
			Result = a | b;
		end
		if (Op[1:0] == 2'b10) begin
			{CarryOut, Result} = Op[2] + a + b;
		end
		Zero = ~Result;
	end
endmodule

Assignment-2/A1/tb_1-bit_ALU.v
/*
	K Rahul Reddy	17CO119
	Sushruth V	17CO148
	24 October 2018

    We toggle A, B, CarryIn, Op code to get all possible cases.
    CarryOut is not calculated for 'AND' and 'OR' operations.
    Op codes of the form 'xx11' are not evaluated. i.e, SLT not implemented.
*/
`include "1-bit_ALU.v"

module tb_one_bit_ALU;
    initial begin
        $dumpfile("one_bit_ALU.vcd");
        $dumpvars(0, tb_one_bit_ALU);
    end
    wire Result, Zero, CarryOut;
    reg A, B, CarryIn;
    reg[3:0] Op;
    integer i;
    one_bit_ALU oba (Result, Zero, CarryOut, A, B, CarryIn, Op[3:0]);
    initial begin
        B = 0;
        repeat (128) begin
        #1   B = ~B;
        end
    end
    initial begin
        A = 0;
        repeat (64) begin
        #2   A = ~A;
        end
    end
    initial begin
        CarryIn = 0;
        repeat (32) begin
        #4   CarryIn = ~CarryIn;
        end
    end
    initial begin
        Op = 4'b0000;
        repeat (16) begin
        #8   Op = Op + 1'b1;
        end       
    end

    initial begin
    for(i = 0; i < 128; i++)
    #1  $display("\nTime = %4d\nA = %3d\t\tB = %3d\nOp Code = %4b\t\tCarry In = %3b\n\nResult = %3d\t\tZero = %3d\t\tCarry Out = %b\n", $time,  A, B, Op[3:0], CarryIn,  Result, Zero, CarryOut);
        
    end
endmodule

Assignment-2/A1/one_bit_ALU.vcd
$date
	Thu Oct 25 21:27:43 2018
$end
$version
	Icarus Verilog
$end
$timescale
	1s
$end
$scope module tb_one_bit_ALU $end
$var wire 1 ! Zero $end
$var wire 1 " Result $end
$var wire 1 # CarryOut $end
$var reg 1 $ A $end
$var reg 1 % B $end
$var reg 1 & CarryIn $end
$var reg 4 ' Op [3:0] $end
$var integer 32 ( i [31:0] $end
$scope module oba $end
$var wire 1 $ A $end
$var wire 1 % B $end
$var wire 1 & CarryIn $end
$var wire 4 ) Op [3:0] $end
$var reg 1 # CarryOut $end
$var reg 1 " Result $end
$var reg 1 ! Zero $end
$var reg 1 * a $end
$var reg 1 + b $end
$upscope $end
$upscope $end
$enddefinitions $end
#0
$dumpvars
0+
0*
b0 )
b0 (
b0 '
0&
0%
0$
x#
0"
1!
$end
#1
1+
b1 (
1%
#2
0+
1*
b10 (
0%
1$
#3
0!
1"
1+
b11 (
1%
#4
1!
0"
0+
0*
b100 (
0%
0$
1&
#5
1+
b101 (
1%
#6
0+
1*
b110 (
0%
1$
#7
0!
1"
1+
b111 (
1%
#8
1!
0"
0+
0*
b1000 (
0%
0$
0&
b1 '
b1 )
#9
0!
1"
1+
b1001 (
1%
#10
0+
1*
b1010 (
0%
1$
#11
1+
b1011 (
1%
#12
1!
0"
0+
0*
b1100 (
0%
0$
1&
#13
0!
1"
1+
b1101 (
1%
#14
0+
1*
b1110 (
0%
1$
#15
1+
b1111 (
1%
#16
1!
0#
0"
0+
0*
b10000 (
0%
0$
0&
b10 '
b10 )
#17
0!
1"
1+
b10001 (
1%
#18
0+
1*
b10010 (
0%
1$
#19
1!
1#
0"
1+
b10011 (
1%
#20
0#
0+
0*
b10100 (
0%
0$
1&
#21
0!
1"
1+
b10101 (
1%
#22
0+
1*
b10110 (
0%
1$
#23
1!
1#
0"
1+
b10111 (
1%
#24
0+
0*
b11000 (
0%
0$
0&
b11 '
b11 )
#25
1+
b11001 (
1%
#26
0+
1*
b11010 (
0%
1$
#27
1+
b11011 (
1%
#28
0+
0*
b11100 (
0%
0$
1&
#29
1+
b11101 (
1%
#30
0+
1*
b11110 (
0%
1$
#31
1+
b11111 (
1%
#32
0*
b100000 (
0%
0$
0&
b100 '
b100 )
#33
0+
b100001 (
1%
#34
0!
1"
1+
1*
b100010 (
0%
1$
#35
1!
0"
0+
b100011 (
1%
#36
1+
0*
b100100 (
0%
0$
1&
#37
0+
b100101 (
1%
#38
0!
1"
1+
1*
b100110 (
0%
1$
#39
1!
0"
0+
b100111 (
1%
#40
0!
1"
1+
0*
b101000 (
0%
0$
0&
b101 '
b101 )
#41
1!
0"
0+
b101001 (
1%
#42
0!
1"
1+
1*
b101010 (
0%
1$
#43
0+
b101011 (
1%
#44
1+
0*
b101100 (
0%
0$
1&
#45
1!
0"
0+
b101101 (
1%
#46
0!
1"
1+
1*
b101110 (
0%
1$
#47
0+
b101111 (
1%
#48
1!
0"
1+
0*
b110000 (
0%
0$
0&
b110 '
b110 )
#49
0!
0#
1"
0+
b110001 (
1%
#50
1#
1+
1*
b110010 (
0%
1$
#51
1!
0"
0+
b110011 (
1%
#52
1+
0*
b110100 (
0%
0$
1&
#53
0!
0#
1"
0+
b110101 (
1%
#54
1#
1+
1*
b110110 (
0%
1$
#55
1!
0"
0+
b110111 (
1%
#56
1+
0*
b111000 (
0%
0$
0&
b111 '
b111 )
#57
0+
b111001 (
1%
#58
1+
1*
b111010 (
0%
1$
#59
0+
b111011 (
1%
#60
1+
0*
b111100 (
0%
0$
1&
#61
0+
b111101 (
1%
#62
1+
1*
b111110 (
0%
1$
#63
0+
b111111 (
1%
#64
b1000000 (
0%
0$
0&
b1000 '
b1000 )
#65
0!
1"
1+
b1000001 (
1%
#66
1!
0"
0+
0*
b1000010 (
0%
1$
#67
1+
b1000011 (
1%
#68
0+
1*
b1000100 (
0%
0$
1&
#69
0!
1"
1+
b1000101 (
1%
#70
1!
0"
0+
0*
b1000110 (
0%
1$
#71
1+
b1000111 (
1%
#72
0!
1"
0+
1*
b1001000 (
0%
0$
0&
b1001 '
b1001 )
#73
1+
b1001001 (
1%
#74
1!
0"
0+
0*
b1001010 (
0%
1$
#75
0!
1"
1+
b1001011 (
1%
#76
0+
1*
b1001100 (
0%
0$
1&
#77
1+
b1001101 (
1%
#78
1!
0"
0+
0*
b1001110 (
0%
1$
#79
0!
1"
1+
b1001111 (
1%
#80
0#
0+
1*
b1010000 (
0%
0$
0&
b1010 '
b1010 )
#81
1!
1#
0"
1+
b1010001 (
1%
#82
0#
0+
0*
b1010010 (
0%
1$
#83
0!
1"
1+
b1010011 (
1%
#84
0+
1*
b1010100 (
0%
0$
1&
#85
1!
1#
0"
1+
b1010101 (
1%
#86
0#
0+
0*
b1010110 (
0%
1$
#87
0!
1"
1+
b1010111 (
1%
#88
0+
1*
b1011000 (
0%
0$
0&
b1011 '
b1011 )
#89
1+
b1011001 (
1%
#90
0+
0*
b1011010 (
0%
1$
#91
1+
b1011011 (
1%
#92
0+
1*
b1011100 (
0%
0$
1&
#93
1+
b1011101 (
1%
#94
0+
0*
b1011110 (
0%
1$
#95
1+
b1011111 (
1%
#96
1*
b1100000 (
0%
0$
0&
b1100 '
b1100 )
#97
1!
0"
0+
b1100001 (
1%
#98
1+
0*
b1100010 (
0%
1$
#99
0+
b1100011 (
1%
#100
0!
1"
1+
1*
b1100100 (
0%
0$
1&
#101
1!
0"
0+
b1100101 (
1%
#102
1+
0*
b1100110 (
0%
1$
#103
0+
b1100111 (
1%
#104
0!
1"
1+
1*
b1101000 (
0%
0$
0&
b1101 '
b1101 )
#105
0+
b1101001 (
1%
#106
1+
0*
b1101010 (
0%
1$
#107
1!
0"
0+
b1101011 (
1%
#108
0!
1"
1+
1*
b1101100 (
0%
0$
1&
#109
0+
b1101101 (
1%
#110
1+
0*
b1101110 (
0%
1$
#111
1!
0"
0+
b1101111 (
1%
#112
0!
1#
1"
1+
1*
b1110000 (
0%
0$
0&
b1110 '
b1110 )
#113
1!
0"
0+
b1110001 (
1%
#114
1+
0*
b1110010 (
0%
1$
#115
0!
0#
1"
0+
b1110011 (
1%
#116
1#
1+
1*
b1110100 (
0%
0$
1&
#117
1!
0"
0+
b1110101 (
1%
#118
1+
0*
b1110110 (
0%
1$
#119
0!
0#
1"
0+
b1110111 (
1%
#120
1+
1*
b1111000 (
0%
0$
0&
b1111 '
b1111 )
#121
0+
b1111001 (
1%
#122
1+
0*
b1111010 (
0%
1$
#123
0+
b1111011 (
1%
#124
1+
1*
b1111100 (
0%
0$
1&
#125
0+
b1111101 (
1%
#126
1+
0*
b1111110 (
0%
1$
#127
0+
b1111111 (
1%
#128
1!
0"
b10000000 (
0%
0$
0&
b0 '
b0 )
