Assignment-1/A3/halfAdder.v
/*
	K Rahul Reddy	17CO119
	Sushruth V	17CO148
	15 October 2018
*/


module halfAdder (output reg sum, output reg carry, input op1, input op2);
	always @ (op1 or op2) begin		//if inputs are 0 and 0, thread is not executed
		sum = op1 ^ op2;		// sum bit of two operands
		carry = op1 & op2;		// carry bit of two operands
	end
endmodule

Assignment-1/A4/fullAdder.v
/*
	K Rahul Reddy	17CO119
	Sushruth V	17CO148
	15 October 2018
*/

`include "halfAdder.v"

module fullAdder (output sum, output carry, input op1, input op2,input op3);
	wire tempSum,t1carry,t2carry;
	halfAdder inst1 (tempSum,t1carry,op1,op2);	// sum of first two bits
	halfAdder inst2 (sum,t2carry,tempSum,op3);	// calculating the sum
	assign carry = t1carry|t2carry;			// calculating the carry
endmodule

Assignment-1/A5/tb_subtractor.v
/*
	K Rahul Reddy	17CO119
	Sushruth V	17CO148
	15 October 2018
*/

`include "fullAdder.v"

module tb_Subtractor;
	initial begin
		$dumpfile("Sub.vcd");	
		$dumpvars(0, tb_Subtractor);
	end	
	wire sum, carry;		//outputs
	reg op1, op2, op3;		//inputs
	//n1 and n2 are the numbers. By replacing 3 by (n-1), we can add n-bit numbers.
	reg[3:0] n1;
	reg[3:0] n2;	
	reg imm;		// Immediate value
	integer i;	
	fullAdder inst (sum, carry, op1, op2, op3);	// Full Adder thread instantiated
	initial begin
		n1=6;	//random values n1 and n2
		n2=9;		
		imm=1;		
		op1=1'b0;
		op2=1'b0;
		op3=1'b0;
		$display("%d -%d = ",n1,n2);
		$display("Bits from LSB to MSB in order are as follows");
		//3 must be replaced by (n - 1)
		for (i=0;i<=3;i=i+1) begin
		#10	op1=n1[i];				
			op2=~n2[i];
			op3=imm;
			assign imm=carry;
		#10	$display("%b",sum);	// Displaying the sum bit
		end	
		
		$display("%b",~carry);	// displaying the last carry bit 
	end		
endmodule

Assignment-1/A5/Sub.vcd
$date
	Mon Oct 15 22:52:18 2018
$end
$version
	Icarus Verilog
$end
$timescale
	1s
$end
$scope module tb_Subtractor $end
$var wire 1 ! sum $end
$var wire 1 " carry $end
$var reg 1 # imm $end
$var reg 4 $ n1 [3:0] $end
$var reg 4 % n2 [3:0] $end
$var reg 1 & op1 $end
$var reg 1 ' op2 $end
$var reg 1 ( op3 $end
$var integer 32 ) i [31:0] $end
$scope module inst $end
$var wire 1 " carry $end
$var wire 1 & op1 $end
$var wire 1 ' op2 $end
$var wire 1 ( op3 $end
$var wire 1 * tempSum $end
$var wire 1 + t2carry $end
$var wire 1 , t1carry $end
$var wire 1 ! sum $end
$scope module inst1 $end
$var wire 1 & op1 $end
$var wire 1 ' op2 $end
$var reg 1 , carry $end
$var reg 1 * sum $end
$upscope $end
$scope module inst2 $end
$var wire 1 * op1 $end
$var wire 1 ( op2 $end
$var reg 1 + carry $end
$var reg 1 ! sum $end
$upscope $end
$upscope $end
$upscope $end
$enddefinitions $end
#0
$dumpvars
0,
0+
0*
b0 )
0(
0'
0&
b1001 %
b110 $
1#
0"
0!
$end
#10
1!
0#
1(
#20
b1 )
#30
1#
1"
0!
1,
0(
1'
1&
#40
b10 )
#50
1!
1(
#60
b11 )
#70
0#
0"
0,
0'
0&
#80
b100 )
