Assignment-1/A2/Encoder/encoder.v
/*
	K Rahul Reddy	17CO119
	Sushruth V	17CO148
	15 October 2018
*/

module encoder (output reg [0:3] out, input [0:15] in);	
	always @ (in) begin			
		case (in)       //switch to give 4-bit output corresponding to 16-bit input
			16'b0000000000000001	: out = 4'b0000; 
			16'b0000000000000010	: out = 4'b0001; 
			16'b0000000000000100	: out = 4'b0010; 
			16'b0000000000001000	: out = 4'b0011; 
			16'b0000000000010000	: out = 4'b0100; 
			16'b0000000000100000	: out = 4'b0101; 
			16'b0000000001000000	: out = 4'b0110; 
			16'b0000000010000000	: out = 4'b0111; 
			16'b0000000100000000	: out = 4'b1000; 
			16'b0000001000000000	: out = 4'b1001; 
			16'b0000010000000000	: out = 4'b1010; 
			16'b0000100000000000	: out = 4'b1011; 
			16'b0001000000000000	: out = 4'b1100; 
			16'b0010000000000000	: out = 4'b1101; 
			16'b0100000000000000	: out = 4'b1110; 
			16'b1000000000000000	: out = 4'b1111;
			default			: out = 4'bxxxx; 
		endcase		
	end
endmodule

Assignment-1/A2/Encoder/tb_encoder.v
/*
	K Rahul Reddy	17CO119
	Sushruth V	17CO148
	15 October 2018
*/
`include "encoder.v"
module tb_encoder;
	initial begin
		$dumpfile("tb_encoder.vcd");
		$dumpvars(0, tb_encoder);
	end	
	wire[0:3] out;		//output is a set of 3 wires
	reg[0:15] in;		// input is 16-bit register
	
	encoder inst (out, in);	// instantiating encoder module
	
	initial begin		// check for various input combinations
		in = 16'b0000000000000001;
		#10
		in = 16'b0000000000000010;
		#10
		in = 16'b0000000000000100;
		#10
		in = 16'b0000000000001000;
		#10
		in = 16'b0000000000010000;	
		#10
		in = 16'b0000000000100000;	
		#10
		in = 16'b0000000001000000;	
		#10
		in = 16'b0000000010000000;
		#10
		in = 16'b0000000100000000;		
		#10
		in = 16'b0000001000000000;	
		#10
		in = 16'b0000010000000000;	
		#10
		in = 16'b0000100000000000;	
		#10
		in = 16'b0001000000000000;
		#10
		in = 16'b0010000000000000;		
		#10
		in = 16'b0100000000000000;		
		#10
		in = 16'b1000000000000000;	
		#10;						
	end	
	initial begin			// print result
		$monitor("%t: input: %b output: %b", $time, in, out);	
	end
endmodule

Assignment-1/A2/Encoder/tb_encoder.vcd
$date
	Mon Oct 15 21:12:42 2018
$end
$version
	Icarus Verilog
$end
$timescale
	1s
$end
$scope module tb_encoder $end
$var wire 4 ! out [0:3] $end
$var reg 16 " in [0:15] $end
$scope module inst $end
$var wire 16 # in [0:15] $end
$var reg 4 $ out [0:3] $end
$upscope $end
$upscope $end
$enddefinitions $end
#0
$dumpvars
b0 $
b1 #
b1 "
b0 !
$end
#10
b1 !
b1 $
b10 "
b10 #
#20
b10 !
b10 $
b100 "
b100 #
#30
b11 !
b11 $
b1000 "
b1000 #
#40
b100 !
b100 $
b10000 "
b10000 #
#50
b101 !
b101 $
b100000 "
b100000 #
#60
b110 !
b110 $
b1000000 "
b1000000 #
#70
b111 !
b111 $
b10000000 "
b10000000 #
#80
b1000 !
b1000 $
b100000000 "
b100000000 #
#90
b1001 !
b1001 $
b1000000000 "
b1000000000 #
#100
b1010 !
b1010 $
b10000000000 "
b10000000000 #
#110
b1011 !
b1011 $
b100000000000 "
b100000000000 #
#120
b1100 !
b1100 $
b1000000000000 "
b1000000000000 #
#130
b1101 !
b1101 $
b10000000000000 "
b10000000000000 #
#140
b1110 !
b1110 $
b100000000000000 "
b100000000000000 #
#150
b1111 !
b1111 $
b1000000000000000 "
b1000000000000000 #
