Assignment-1/A3/halfAdder.v
/*
	K Rahul Reddy	17CO119
	Sushruth V	17CO148
	15 October 2018
*/


module halfAdder (output reg sum, output reg carry, input op1, input op2);
	always @ (op1 or op2) begin		//if inputs are 0 and 0, thread is not executed
		sum = op1 ^ op2;		// sum bit of two operands
		carry = op1 & op2;		// carry bit of two operands
	end
endmodule

Assignment-1/A4/fullAdder.v
/*
	K Rahul Reddy	17CO119
	Sushruth V	17CO148
	15 October 2018
*/

`include "halfAdder.v"

module fullAdder (output sum, output carry, input op1, input op2,input op3);
	wire tempSum,t1carry,t2carry;
	halfAdder inst1 (tempSum,t1carry,op1,op2);	// sum of first two bits
	halfAdder inst2 (sum,t2carry,tempSum,op3);	// calculating the sum
	assign carry = t1carry|t2carry;			// calculating the carry
endmodule

Assignment-1/A4/tb_fullAdder.v
/*
	K Rahul Reddy	17CO119
	Sushruth V	17CO148
	15 October 2018
*/
`include "fullAdder.v"

module main;
	initial begin
		$dumpfile("tb_fullAdder.vcd");	
		$dumpvars(0, main);
	end
	wire sum, carry;		//outputs
	reg op1,op2, op3;			//inputs 	
	reg[3:0] n1;
	reg[3:0] n2;
	reg[3:0] n3;
	integer i, j;
	fullAdder inst (sum, carry, op1, op2, op3);		//instantiating full adder
	initial begin
		n1 = 3;
		n2 = 5;
		n3 = 2;
        	op1 = 1'b0;
        	op2 = 1'b0;
		op3 = 1'b0;
        	for (j = 0;j <= 1;j = j + 1) begin
            		for(i = 0;i <= 3;i = i + 1) begin
                	#1	$display("Sum of %d, %d and %d",n1[i],n2[i],n3[j]);
			#1	op1=n1[i];		//input fields		
			    	op2=n2[i];
			    	op3=n3[j];
	    	    	#1	$display("Sum=%d\nCarry=%d\n",sum,carry);	// Displaying the sum and carry bits
			end
        	end
	end
endmodule

Assignment-1/A4/tb_fullAdder.vcd
$date
	Mon Oct 15 22:04:52 2018
$end
$version
	Icarus Verilog
$end
$timescale
	1s
$end
$scope module main $end
$var wire 1 ! sum $end
$var wire 1 " carry $end
$var reg 4 # n1 [3:0] $end
$var reg 4 $ n2 [3:0] $end
$var reg 4 % n3 [3:0] $end
$var reg 1 & op1 $end
$var reg 1 ' op2 $end
$var reg 1 ( op3 $end
$var integer 32 ) i [31:0] $end
$var integer 32 * j [31:0] $end
$scope module inst $end
$var wire 1 " carry $end
$var wire 1 & op1 $end
$var wire 1 ' op2 $end
$var wire 1 ( op3 $end
$var wire 1 + tempSum $end
$var wire 1 , t2carry $end
$var wire 1 - t1carry $end
$var wire 1 ! sum $end
$scope module inst1 $end
$var wire 1 & op1 $end
$var wire 1 ' op2 $end
$var reg 1 - carry $end
$var reg 1 + sum $end
$upscope $end
$scope module inst2 $end
$var wire 1 + op1 $end
$var wire 1 ( op2 $end
$var reg 1 , carry $end
$var reg 1 ! sum $end
$upscope $end
$upscope $end
$upscope $end
$enddefinitions $end
#0
$dumpvars
0-
0,
0+
b0 *
b0 )
0(
0'
0&
b10 %
b101 $
b11 #
0"
0!
$end
#2
1"
1-
1'
1&
#3
b1 )
#5
0"
1!
0-
1+
0'
#6
b10 )
#8
1'
0&
#9
b11 )
#11
0!
0+
0'
#12
b1 *
b0 )
#14
1"
1!
1-
1(
1'
1&
#15
b1 )
#17
1,
0!
0-
1+
0'
#18
b10 )
#20
1'
0&
#21
b11 )
#23
0"
0,
1!
0+
0'
#24
b10 *
b100 )
