Assignment-2/A2/64-bit_ALU.v
/*
	K Rahul Reddy	17CO119
	Sushruth V	17CO148
	24 October 2018

	Op-Code : 4-bits
	bit 1 : neg_A
	bit 2 : neg_B
	bit 3,4 : indicate component
				00 => and
				01 => or
				10 => add

*/

module ALU(output reg[63:0] Result, output reg Zero, output reg CarryOut, input[63:0] A, input[63:0] B, input CarryIn, input[3:0] Op);
    reg[63:0] a;
	reg[63:0] b;
    integer i;
	always@(A, B, CarryIn, Op) begin
		for(i = 0; i < 64; i++) begin
            a[i] = (~A[i] & Op[3]) | (A[i] & ~Op[3]);
		    b[i] = (~B[i] & Op[2]) | (B[i] & ~Op[2]);
        end
		if (Op[1:0] == 2'b00) begin
		    for(i = 0; i < 64; i++) 
                Result[i] = a[i] & b[i];        
		end
		if (Op[1:0] == 2'b01) begin
			for(i = 0; i < 64; i++) 
                Result[i] = a[i] | b[i];        
		end
		if (Op[1:0] == 2'b10) begin
			{CarryOut, Result} = Op[2] + a + b;
		end
		if(Result != 0)
            Zero = 0;
        if(Result == 0)
            Zero = 1;
	end
endmodule

Assignment-2/A3/CU.v
/*
        K Rahul Reddy	17CO119
        Sushruth V	17CO148
        24 October 2018

        funct7[5] and funct3[2:0] are required to identify operation.
*/
module CU(output [3:0] Op, input[1:0] ALU_Op, input[6:0] funct7, input[2:0] funct3);
    wire F0 = funct3[0];
    wire F1 = funct3[1];
    wire F2 = funct3[2];
    wire F3 = funct7[5]; 
    assign Op[3] = 0;
    assign Op[2] = ALU_Op[0] | (ALU_Op[1] & F3 & ~F2 & ~F1 & ~F0);
    assign Op[1] = ~F1 | ~ALU_Op[1];
    assign Op[0] = ALU_Op[1] & F1 & ~F0;
endmodule

Assignment-2/A4/tb_ALU.v
/*
        K Rahul Reddy	17CO119
        Sushruth V	17CO148
        24 October 2018
*/
`include "CU.v"
`include "64-bit_ALU.v"

module tb_ALU;
    initial begin
        $dumpfile("ALU.vcd");
        $dumpvars(0, tb_ALU);
    end
    reg[1:0] ALU_Op;
    reg[6:0] funct7;
    reg[2:0] funct3;
    wire[3:0] Op;
    integer i, j;
    reg[63:0] A;
    reg[63:0] B;
    wire[63:0] Result;
    reg CarryIn;
    wire Zero, CarryOut;
    CU inst(Op, ALU_Op, funct7, funct3);
    ALU alu1(Result, Zero, CarryOut, A, B, CarryIn, Op);
    initial begin
    for(j = 0; j < 4; j++) begin
    #20 ALU_Op = 2'b00;
        CarryIn = Op[2];
        funct7 = 7'b0100111;
        funct3 = 3'b111;
        $display("Case 0: Add(ALU_Op code)\n\n");
    #20    ALU_Op = 2'b01;
        CarryIn = Op[2];
        funct7 = 7'b0000000;
        funct3 = 3'b111;
        $display("Case 1: Subtract(ALU_Op code)\n\n");
    #20 ALU_Op = 2'b10;
        CarryIn = Op[2];
        funct7 = 7'b0000000;
        funct3 = 3'b000;
        $display("Case 2: Add(R-type)\n\n");
    #20 ALU_Op = 2'b10;
        CarryIn = Op[2];
        funct7 = 7'b0100000;
        funct3 = 3'b000;
        $display("Case 3: Subtract(R-type)\n\n");
    #20 ALU_Op = 2'b10;
        CarryIn = Op[2];
        funct7 = 7'b0000000;
        funct3 = 3'b111;
        $display("Case 4: And(R-type)\n\n");
    #20 ALU_Op = 2'b10;
        CarryIn = Op[2];
        funct7 = 7'b0000000;
        funct3 = 3'b110;
        $display("Case 5: Or(R-type)\n\n");
    end
    end
    initial begin
        A = 1;                                  //A= 1
        B = -64'h1;                             //B = -1
    #120
        A = 64'h7fffffffffffffff;                             //A = max
        B = 1;                                                //B = 1
    #120
        A = 64'h7fffffffffffffff;               //A = max
        B = 64'h8000000000000000;               //b = min
    #120
        A = 0;
        B = 0;
    end
    initial begin
    #1;
        for(i = 0; i < 24; i++) begin
    #20     $display("ALU_Op = %3b\t\tfunct7 = %8b\t\tfunct3 = %4b\n\nOpcode = %b\n", ALU_Op, funct7, funct3, Op);
            $display("Time = %4d\nA = %10h\t\tB = %10h\t\tCarry In = %3b\n\nResult = %10h\t\tZero = %3d\t\tCarry Out = %b\n\n\n", $time, A[63:0], B[63:0], CarryIn,  Result[63:0], Zero, CarryOut);
        end
    end
endmodule

Assignment-2/A4/ALU.vcd
$date
	Fri Oct 26 00:31:59 2018
$end
$version
	Icarus Verilog
$end
$timescale
	1s
$end
$scope module tb_ALU $end
$var wire 1 ! Zero $end
$var wire 64 " Result [63:0] $end
$var wire 4 # Op [3:0] $end
$var wire 1 $ CarryOut $end
$var reg 64 % A [63:0] $end
$var reg 2 & ALU_Op [1:0] $end
$var reg 64 ' B [63:0] $end
$var reg 1 ( CarryIn $end
$var reg 3 ) funct3 [2:0] $end
$var reg 7 * funct7 [6:0] $end
$var integer 32 + i [31:0] $end
$var integer 32 , j [31:0] $end
$scope module alu1 $end
$var wire 64 - A [63:0] $end
$var wire 64 . B [63:0] $end
$var wire 1 ( CarryIn $end
$var wire 4 / Op [3:0] $end
$var reg 1 $ CarryOut $end
$var reg 64 0 Result [63:0] $end
$var reg 1 ! Zero $end
$var reg 64 1 a [63:0] $end
$var reg 64 2 b [63:0] $end
$var integer 32 3 i [31:0] $end
$upscope $end
$scope module inst $end
$var wire 2 4 ALU_Op [1:0] $end
$var wire 3 5 funct3 [2:0] $end
$var wire 7 6 funct7 [6:0] $end
$var wire 4 7 Op [3:0] $end
$var wire 1 8 F3 $end
$var wire 1 9 F2 $end
$var wire 1 : F1 $end
$var wire 1 ; F0 $end
$upscope $end
$upscope $end
$enddefinitions $end
#0
$dumpvars
x;
x:
x9
x8
b0xxx 7
bx 6
bx 5
bx 4
b1000000 3
bx 2
b1 1
bx 0
b0xxx /
b1111111111111111111111111111111111111111111111111111111111111111 .
b1 -
b0 ,
bx +
bx *
bx )
x(
b1111111111111111111111111111111111111111111111111111111111111111 '
bx &
b1 %
x$
b0xxx #
bx "
x!
$end
#1
b0 +
#20
1!
1$
b0 "
b0 0
b1111111111111111111111111111111111111111111111111111111111111111 2
b1000000 3
b10 #
b10 /
b10 7
1;
1:
19
18
b111 )
b111 5
b100111 *
b100111 6
b0 &
b0 4
#21
b1 +
#40
0!
0$
b10 "
b10 0
b0 2
b110 #
b110 /
b110 7
08
b1000000 3
b0 *
b0 6
0(
b1 &
b1 4
#41
b10 +
#60
1!
1$
b0 "
b0 0
b1111111111111111111111111111111111111111111111111111111111111111 2
b10 #
b10 /
b10 7
0;
0:
09
b1000000 3
b0 )
b0 5
1(
b10 &
b10 4
#61
b11 +
#80
0!
0$
b10 "
b10 0
b0 2
b110 #
b110 /
b110 7
18
b1000000 3
b100000 *
b100000 6
0(
#81
b100 +
#100
b1111111111111111111111111111111111111111111111111111111111111111 2
0!
b1 "
b1 0
b0 #
b0 /
b0 7
1;
1:
19
08
b1000000 3
b111 )
b111 5
b0 *
b0 6
1(
#101
b101 +
#120
b111111111111111111111111111111111111111111111111111111111111111 "
b111111111111111111111111111111111111111111111111111111111111111 0
b1 #
b1 /
b1 7
0;
b1 2
b111111111111111111111111111111111111111111111111111111111111111 1
b1000000 3
b1 ,
b110 )
b110 5
0(
b1 '
b1 .
b111111111111111111111111111111111111111111111111111111111111111 %
b111111111111111111111111111111111111111111111111111111111111111 -
#121
b110 +
#140
b1000000000000000000000000000000000000000000000000000000000000000 "
b1000000000000000000000000000000000000000000000000000000000000000 0
b1000000 3
b10 #
b10 /
b10 7
1;
18
b111 )
b111 5
b100111 *
b100111 6
b0 &
b0 4
#141
b111 +
#160
1$
b111111111111111111111111111111111111111111111111111111111111110 "
b111111111111111111111111111111111111111111111111111111111111110 0
b1111111111111111111111111111111111111111111111111111111111111110 2
b1000000 3
b110 #
b110 /
b110 7
08
b0 *
b0 6
b1 &
b1 4
#161
b1000 +
#180
0$
b1000000000000000000000000000000000000000000000000000000000000000 "
b1000000000000000000000000000000000000000000000000000000000000000 0
b1 2
b10 #
b10 /
b10 7
0;
0:
09
b1000000 3
b0 )
b0 5
1(
b10 &
b10 4
#181
b1001 +
#200
1$
b111111111111111111111111111111111111111111111111111111111111110 "
b111111111111111111111111111111111111111111111111111111111111110 0
b1111111111111111111111111111111111111111111111111111111111111110 2
b110 #
b110 /
b110 7
18
b1000000 3
b100000 *
b100000 6
0(
#201
b1010 +
#220
b1 "
b1 0
b1 2
b0 #
b0 /
b0 7
1;
1:
19
08
b1000000 3
b111 )
b111 5
b0 *
b0 6
1(
#221
b1011 +
#240
b1 #
b1 /
b1 7
0;
0!
b1111111111111111111111111111111111111111111111111111111111111111 "
b1111111111111111111111111111111111111111111111111111111111111111 0
b1000000000000000000000000000000000000000000000000000000000000000 2
b1000000 3
b10 ,
b110 )
b110 5
0(
b1000000000000000000000000000000000000000000000000000000000000000 '
b1000000000000000000000000000000000000000000000000000000000000000 .
#241
b1100 +
#260
0$
b1000000 3
b10 #
b10 /
b10 7
1;
18
b111 )
b111 5
b100111 *
b100111 6
b0 &
b0 4
#261
b1101 +
#280
b111111111111111111111111111111111111111111111111111111111111111 2
b1000000 3
b110 #
b110 /
b110 7
08
b0 *
b0 6
b1 &
b1 4
#281
b1110 +
#300
b1000000000000000000000000000000000000000000000000000000000000000 2
b10 #
b10 /
b10 7
0;
0:
09
b1000000 3
b0 )
b0 5
1(
b10 &
b10 4
#301
b1111 +
#320
b111111111111111111111111111111111111111111111111111111111111111 2
b110 #
b110 /
b110 7
18
b1000000 3
b100000 *
b100000 6
0(
#321
b10000 +
#340
1!
b1000000000000000000000000000000000000000000000000000000000000000 2
b0 "
b0 0
b0 #
b0 /
b0 7
1;
1:
19
08
b1000000 3
b111 )
b111 5
b0 *
b0 6
1(
#341
b10001 +
#360
b1 #
b1 /
b1 7
0;
b0 2
b0 1
b1000000 3
b11 ,
b110 )
b110 5
0(
b0 '
b0 .
b0 %
b0 -
#361
b10010 +
#380
b1000000 3
b10 #
b10 /
b10 7
1;
18
b111 )
b111 5
b100111 *
b100111 6
b0 &
b0 4
#381
b10011 +
#400
1$
b1111111111111111111111111111111111111111111111111111111111111111 2
b1000000 3
b110 #
b110 /
b110 7
08
b0 *
b0 6
b1 &
b1 4
#401
b10100 +
#420
0$
b0 2
b10 #
b10 /
b10 7
0;
0:
09
b1000000 3
b0 )
b0 5
1(
b10 &
b10 4
#421
b10101 +
#440
1$
b1111111111111111111111111111111111111111111111111111111111111111 2
b110 #
b110 /
b110 7
18
b1000000 3
b100000 *
b100000 6
0(
#441
b10110 +
#460
b0 2
b0 #
b0 /
b0 7
1;
1:
19
08
b1000000 3
b111 )
b111 5
b0 *
b0 6
1(
#461
b10111 +
#480
b1 #
b1 /
b1 7
0;
b1000000 3
b100 ,
b110 )
b110 5
0(
#481
b11000 +
