Assignment-2/A5/Reg32b.v
/*
	K Rahul Reddy	17CO119
	Sushruth V	17CO148
	25 October 2018

*/

module Reg32b (input [31:0] Data_Write , input Write, output reg [31:0] Data);
    
    initial begin
        Data <= 32'b00000000000000000000000000000000;
    end

    always @ (Write or Data_Write) begin
        if (Write == 1'b1)
            Data <= Data_Write;
        else
            Data <= Data;
    end
endmodule

Assignment-2/A5/register_file.v
/*
	K Rahul Reddy	17CO119
	Sushruth V	17CO148
	25 October 2018

*/

`include "Reg32b.v"

module register_file (output reg [31:0] Read_Data1, output reg [31:0] Read_Data2, input RegWrite, input [31:0] Write_Data, input [4:0] Write_Register, input [4:0] Read_Register1, input[4:0] Read_Register2);
    reg [31:0][31:0] Data_Write;
    reg [31:0] Write;
    wire [31:0][31:0] Out;
    integer i;
    Reg32b r0 (Data_Write[0], Write[0], Out[0]);
    Reg32b r1 (Data_Write[1], Write[1], Out[1]);
    Reg32b r2 (Data_Write[2], Write[2], Out[2]);
    Reg32b r3 (Data_Write[3], Write[3], Out[3]);
    Reg32b r4 (Data_Write[4], Write[4], Out[4]);
    Reg32b r5 (Data_Write[5], Write[5], Out[5]);
    Reg32b r6 (Data_Write[6], Write[6], Out[6]);
    Reg32b r7 (Data_Write[7], Write[7], Out[7]);
    Reg32b r8 (Data_Write[8], Write[8], Out[8]);
    Reg32b r9 (Data_Write[9], Write[9], Out[9]);
    Reg32b r10 (Data_Write[10], Write[10], Out[10]);
    Reg32b r11 (Data_Write[11], Write[11], Out[11]);
    Reg32b r12 (Data_Write[12], Write[12], Out[12]);
    Reg32b r13 (Data_Write[13], Write[13], Out[13]);
    Reg32b r14 (Data_Write[14], Write[14], Out[14]);
    Reg32b r15 (Data_Write[15], Write[15], Out[15]);
    Reg32b r16 (Data_Write[16], Write[16], Out[16]);
    Reg32b r17 (Data_Write[17], Write[17], Out[17]);
    Reg32b r18 (Data_Write[18], Write[18], Out[18]);
    Reg32b r19 (Data_Write[19], Write[19], Out[19]);
    Reg32b r20 (Data_Write[20], Write[20], Out[20]);
    Reg32b r21 (Data_Write[21], Write[21], Out[21]);
    Reg32b r22 (Data_Write[22], Write[22], Out[22]);
    Reg32b r23 (Data_Write[23], Write[23], Out[23]);
    Reg32b r24 (Data_Write[24], Write[24], Out[24]);
    Reg32b r25 (Data_Write[25], Write[25], Out[25]);
    Reg32b r26 (Data_Write[26], Write[26], Out[26]);
    Reg32b r27 (Data_Write[27], Write[27], Out[27]);
    Reg32b r28 (Data_Write[28], Write[28], Out[28]);
    Reg32b r29 (Data_Write[29], Write[29], Out[29]);
    Reg32b r30 (Data_Write[30], Write[30], Out[30]);
    Reg32b r31 (Data_Write[31], Write[31], Out[31]);

    always @ (RegWrite or Write_Register or Read_Register1 or Read_Register2 or Write_Data) begin
        if(RegWrite == 1'b1) begin
            Write[Write_Register] <= 1'b1;
            Data_Write[Write_Register] <= Write_Data;
        end

        else begin
            Write[Read_Register1] <= 1'b0;
            Read_Data1 <= Out[Read_Register1];
            Write[Read_Register2] <= 1'b0;
            Read_Data2 <= Out[Read_Register2];
        end

    end
endmodule

Assignment-2/A5/tb_register_file.v
/*
	K Rahul Reddy	17CO119
	Sushruth V	17CO148
	25 October 2018

*/
`include "register_file.v"

module tb_register_file;
    initial begin
        $dumpfile("register_file.vcd");
        $dumpvars(0, tb_register_file);
    end
    wire [31:0] Read_Data1;
    wire [31:0] Read_Data2;
    reg Write;
    reg [4:0] Write_Register, Read_Register1, Read_Register2;
    reg [31:0] Register_Data;
    integer i, j;
    register_file inst (Read_Data1, Read_Data2, Write, Register_Data, Write_Register, Read_Register1, Read_Register2);
    initial begin
        Write = 1'b1;
        Read_Register1 = 5'b00000;
        Read_Register2 = 5'b00000;
        Write_Register = 5'b00011;
        Register_Data = 32'b10101011100010111101011010010101;
        for (i = 0; i < 31; i++) begin
        #10 Write = 1'b0;
            Write_Register = Write_Register + 1'b1;
            Register_Data = Register_Data + 1'b1;
            Write = 1'b1;
        end

    #10 Write = 1'b0;
    #10 Read_Register1 = 5'b00000;
    #10 Read_Register2 = 5'b00001;

        Write_Register = 5'b00000;
        Register_Data = 32'b00111001110011100111111110011110;
    
    #10 Write = 1'b1;
    
    #10 Write = 1'b0;

    #10 Write_Register = 5'b00001;
        Register_Data = 32'b11000000000100000000010000100000;
    #10 Write = 1'b1;
    
    #10 Write = 1'b0;
    #10 Read_Register1 = 5'b11010;
    #10 Read_Register2 = 5'b00011;
    
    #10 Read_Register1 = 5'b00110;
    #10 Read_Register2 = 5'b01001;
    
    #10 Read_Register1 = 5'b10101;
    #10 Read_Register2 = 5'b11101;
    
    #10 Read_Register1 = 5'b00110;
    #10 Read_Register2 = 5'b11001;
    #10;
       
    end
    initial begin
        $monitor("Read Register1 = %d\t\tRead Data1 = %d\nRead Register2 = %d\t\tRead Data2 = %d\n", Read_Register1, Read_Data1, Read_Register2, Read_Data2);
    end
endmodule

Assignment-2/A5/register_file.vcd
$date
	Fri Oct 26 02:44:47 2018
$end
$version
	Icarus Verilog
$end
$timescale
	1s
$end
$scope module tb_register_file $end
$var wire 32 ! Read_Data2 [31:0] $end
$var wire 32 " Read_Data1 [31:0] $end
$var reg 5 # Read_Register1 [4:0] $end
$var reg 5 $ Read_Register2 [4:0] $end
$var reg 32 % Register_Data [31:0] $end
$var reg 1 & Write $end
$var reg 5 ' Write_Register [4:0] $end
$var integer 32 ( i [31:0] $end
$scope module inst $end
$var wire 5 ) Read_Register1 [4:0] $end
$var wire 5 * Read_Register2 [4:0] $end
$var wire 1 & RegWrite $end
$var wire 32 + Write_Data [31:0] $end
$var wire 5 , Write_Register [4:0] $end
$var wire 1024 - Out [1023:0] $end
$var reg 1024 . Data_Write [1023:0] $end
$var reg 32 / Read_Data1 [31:0] $end
$var reg 32 0 Read_Data2 [31:0] $end
$var reg 32 1 Write [31:0] $end
$scope module r0 $end
$var wire 32 2 Data_Write [31:0] $end
$var wire 1 3 Write $end
$var reg 32 4 Data [31:0] $end
$upscope $end
$scope module r1 $end
$var wire 32 5 Data_Write [31:0] $end
$var wire 1 6 Write $end
$var reg 32 7 Data [31:0] $end
$upscope $end
$scope module r10 $end
$var wire 32 8 Data_Write [31:0] $end
$var wire 1 9 Write $end
$var reg 32 : Data [31:0] $end
$upscope $end
$scope module r11 $end
$var wire 32 ; Data_Write [31:0] $end
$var wire 1 < Write $end
$var reg 32 = Data [31:0] $end
$upscope $end
$scope module r12 $end
$var wire 32 > Data_Write [31:0] $end
$var wire 1 ? Write $end
$var reg 32 @ Data [31:0] $end
$upscope $end
$scope module r13 $end
$var wire 32 A Data_Write [31:0] $end
$var wire 1 B Write $end
$var reg 32 C Data [31:0] $end
$upscope $end
$scope module r14 $end
$var wire 32 D Data_Write [31:0] $end
$var wire 1 E Write $end
$var reg 32 F Data [31:0] $end
$upscope $end
$scope module r15 $end
$var wire 32 G Data_Write [31:0] $end
$var wire 1 H Write $end
$var reg 32 I Data [31:0] $end
$upscope $end
$scope module r16 $end
$var wire 32 J Data_Write [31:0] $end
$var wire 1 K Write $end
$var reg 32 L Data [31:0] $end
$upscope $end
$scope module r17 $end
$var wire 32 M Data_Write [31:0] $end
$var wire 1 N Write $end
$var reg 32 O Data [31:0] $end
$upscope $end
$scope module r18 $end
$var wire 32 P Data_Write [31:0] $end
$var wire 1 Q Write $end
$var reg 32 R Data [31:0] $end
$upscope $end
$scope module r19 $end
$var wire 32 S Data_Write [31:0] $end
$var wire 1 T Write $end
$var reg 32 U Data [31:0] $end
$upscope $end
$scope module r2 $end
$var wire 32 V Data_Write [31:0] $end
$var wire 1 W Write $end
$var reg 32 X Data [31:0] $end
$upscope $end
$scope module r20 $end
$var wire 32 Y Data_Write [31:0] $end
$var wire 1 Z Write $end
$var reg 32 [ Data [31:0] $end
$upscope $end
$scope module r21 $end
$var wire 32 \ Data_Write [31:0] $end
$var wire 1 ] Write $end
$var reg 32 ^ Data [31:0] $end
$upscope $end
$scope module r22 $end
$var wire 32 _ Data_Write [31:0] $end
$var wire 1 ` Write $end
$var reg 32 a Data [31:0] $end
$upscope $end
$scope module r23 $end
$var wire 32 b Data_Write [31:0] $end
$var wire 1 c Write $end
$var reg 32 d Data [31:0] $end
$upscope $end
$scope module r24 $end
$var wire 32 e Data_Write [31:0] $end
$var wire 1 f Write $end
$var reg 32 g Data [31:0] $end
$upscope $end
$scope module r25 $end
$var wire 32 h Data_Write [31:0] $end
$var wire 1 i Write $end
$var reg 32 j Data [31:0] $end
$upscope $end
$scope module r26 $end
$var wire 32 k Data_Write [31:0] $end
$var wire 1 l Write $end
$var reg 32 m Data [31:0] $end
$upscope $end
$scope module r27 $end
$var wire 32 n Data_Write [31:0] $end
$var wire 1 o Write $end
$var reg 32 p Data [31:0] $end
$upscope $end
$scope module r28 $end
$var wire 32 q Data_Write [31:0] $end
$var wire 1 r Write $end
$var reg 32 s Data [31:0] $end
$upscope $end
$scope module r29 $end
$var wire 32 t Data_Write [31:0] $end
$var wire 1 u Write $end
$var reg 32 v Data [31:0] $end
$upscope $end
$scope module r3 $end
$var wire 32 w Data_Write [31:0] $end
$var wire 1 x Write $end
$var reg 32 y Data [31:0] $end
$upscope $end
$scope module r30 $end
$var wire 32 z Data_Write [31:0] $end
$var wire 1 { Write $end
$var reg 32 | Data [31:0] $end
$upscope $end
$scope module r31 $end
$var wire 32 } Data_Write [31:0] $end
$var wire 1 ~ Write $end
$var reg 32 !" Data [31:0] $end
$upscope $end
$scope module r4 $end
$var wire 32 "" Data_Write [31:0] $end
$var wire 1 #" Write $end
$var reg 32 $" Data [31:0] $end
$upscope $end
$scope module r5 $end
$var wire 32 %" Data_Write [31:0] $end
$var wire 1 &" Write $end
$var reg 32 '" Data [31:0] $end
$upscope $end
$scope module r6 $end
$var wire 32 (" Data_Write [31:0] $end
$var wire 1 )" Write $end
$var reg 32 *" Data [31:0] $end
$upscope $end
$scope module r7 $end
$var wire 32 +" Data_Write [31:0] $end
$var wire 1 ," Write $end
$var reg 32 -" Data [31:0] $end
$upscope $end
$scope module r8 $end
$var wire 32 ." Data_Write [31:0] $end
$var wire 1 /" Write $end
$var reg 32 0" Data [31:0] $end
$upscope $end
$scope module r9 $end
$var wire 32 1" Data_Write [31:0] $end
$var wire 1 2" Write $end
$var reg 32 3" Data [31:0] $end
$upscope $end
$upscope $end
$upscope $end
$enddefinitions $end
#0
$dumpvars
b0 3"
x2"
bx 1"
b0 0"
x/"
bx ."
b0 -"
x,"
bx +"
b0 *"
x)"
bx ("
b0 '"
x&"
bx %"
b0 $"
x#"
bx ""
b0 !"
x~
bx }
b0 |
x{
bx z
b10101011100010111101011010010101 y
1x
b10101011100010111101011010010101 w
b0 v
xu
bx t
b0 s
xr
bx q
b0 p
xo
bx n
b0 m
xl
bx k
b0 j
xi
bx h
b0 g
xf
bx e
b0 d
xc
bx b
b0 a
x`
bx _
b0 ^
x]
bx \
b0 [
xZ
bx Y
b0 X
xW
bx V
b0 U
xT
bx S
b0 R
xQ
bx P
b0 O
xN
bx M
b0 L
xK
bx J
b0 I
xH
bx G
b0 F
xE
bx D
b0 C
xB
bx A
b0 @
x?
bx >
b0 =
x<
bx ;
b0 :
x9
bx 8
b0 7
x6
bx 5
b0 4
x3
bx 2
bx1xxx 1
bx 0
bx /
bx10101011100010111101011010010101xxxxxxxxxxxxxxxxxxxxxxxxxxxxxxxxxxxxxxxxxxxxxxxxxxxxxxxxxxxxxxxxxxxxxxxxxxxxxxxxxxxxxxxxxxxxxxxx .
b10101011100010111101011010010101000000000000000000000000000000000000000000000000000000000000000000000000000000000000000000000000 -
b11 ,
b10101011100010111101011010010101 +
b0 *
b0 )
b0 (
b11 '
1&
b10101011100010111101011010010101 %
b0 $
b0 #
bx "
bx !
$end
#10
b1010101110001011110101101001011010101011100010111101011010010101000000000000000000000000000000000000000000000000000000000000000000000000000000000000000000000000 -
b10101011100010111101011010010110 $"
b10101011100010111101011010010110 ""
1#"
bx1010101110001011110101101001011010101011100010111101011010010101xxxxxxxxxxxxxxxxxxxxxxxxxxxxxxxxxxxxxxxxxxxxxxxxxxxxxxxxxxxxxxxxxxxxxxxxxxxxxxxxxxxxxxxxxxxxxxxx .
bx11xxx 1
b1 (
b10101011100010111101011010010110 %
b10101011100010111101011010010110 +
b100 '
b100 ,
1&
#20
b101010111000101111010110100101111010101110001011110101101001011010101011100010111101011010010101000000000000000000000000000000000000000000000000000000000000000000000000000000000000000000000000 -
b10101011100010111101011010010111 '"
b10101011100010111101011010010111 %"
1&"
bx101010111000101111010110100101111010101110001011110101101001011010101011100010111101011010010101xxxxxxxxxxxxxxxxxxxxxxxxxxxxxxxxxxxxxxxxxxxxxxxxxxxxxxxxxxxxxxxxxxxxxxxxxxxxxxxxxxxxxxxxxxxxxxxx .
bx111xxx 1
b10 (
b10101011100010111101011010010111 %
b10101011100010111101011010010111 +
b101 '
b101 ,
1&
#30
b10101011100010111101011010011000101010111000101111010110100101111010101110001011110101101001011010101011100010111101011010010101000000000000000000000000000000000000000000000000000000000000000000000000000000000000000000000000 -
b10101011100010111101011010011000 *"
b10101011100010111101011010011000 ("
1)"
bx10101011100010111101011010011000101010111000101111010110100101111010101110001011110101101001011010101011100010111101011010010101xxxxxxxxxxxxxxxxxxxxxxxxxxxxxxxxxxxxxxxxxxxxxxxxxxxxxxxxxxxxxxxxxxxxxxxxxxxxxxxxxxxxxxxxxxxxxxxx .
bx1111xxx 1
b11 (
b10101011100010111101011010011000 %
b10101011100010111101011010011000 +
b110 '
b110 ,
1&
#40
b1010101110001011110101101001100110101011100010111101011010011000101010111000101111010110100101111010101110001011110101101001011010101011100010111101011010010101000000000000000000000000000000000000000000000000000000000000000000000000000000000000000000000000 -
b10101011100010111101011010011001 -"
b10101011100010111101011010011001 +"
1,"
bx1010101110001011110101101001100110101011100010111101011010011000101010111000101111010110100101111010101110001011110101101001011010101011100010111101011010010101xxxxxxxxxxxxxxxxxxxxxxxxxxxxxxxxxxxxxxxxxxxxxxxxxxxxxxxxxxxxxxxxxxxxxxxxxxxxxxxxxxxxxxxxxxxxxxxx .
bx11111xxx 1
b100 (
b10101011100010111101011010011001 %
b10101011100010111101011010011001 +
b111 '
b111 ,
1&
#50
b101010111000101111010110100110101010101110001011110101101001100110101011100010111101011010011000101010111000101111010110100101111010101110001011110101101001011010101011100010111101011010010101000000000000000000000000000000000000000000000000000000000000000000000000000000000000000000000000 -
b10101011100010111101011010011010 0"
b10101011100010111101011010011010 ."
1/"
bx101010111000101111010110100110101010101110001011110101101001100110101011100010111101011010011000101010111000101111010110100101111010101110001011110101101001011010101011100010111101011010010101xxxxxxxxxxxxxxxxxxxxxxxxxxxxxxxxxxxxxxxxxxxxxxxxxxxxxxxxxxxxxxxxxxxxxxxxxxxxxxxxxxxxxxxxxxxxxxxx .
bx111111xxx 1
b101 (
b10101011100010111101011010011010 %
b10101011100010111101011010011010 +
b1000 '
b1000 ,
1&
#60
b10101011100010111101011010011011101010111000101111010110100110101010101110001011110101101001100110101011100010111101011010011000101010111000101111010110100101111010101110001011110101101001011010101011100010111101011010010101000000000000000000000000000000000000000000000000000000000000000000000000000000000000000000000000 -
b10101011100010111101011010011011 3"
b10101011100010111101011010011011 1"
12"
bx10101011100010111101011010011011101010111000101111010110100110101010101110001011110101101001100110101011100010111101011010011000101010111000101111010110100101111010101110001011110101101001011010101011100010111101011010010101xxxxxxxxxxxxxxxxxxxxxxxxxxxxxxxxxxxxxxxxxxxxxxxxxxxxxxxxxxxxxxxxxxxxxxxxxxxxxxxxxxxxxxxxxxxxxxxx .
bx1111111xxx 1
b110 (
b10101011100010111101011010011011 %
b10101011100010111101011010011011 +
b1001 '
b1001 ,
1&
#70
b1010101110001011110101101001110010101011100010111101011010011011101010111000101111010110100110101010101110001011110101101001100110101011100010111101011010011000101010111000101111010110100101111010101110001011110101101001011010101011100010111101011010010101000000000000000000000000000000000000000000000000000000000000000000000000000000000000000000000000 -
b10101011100010111101011010011100 :
b10101011100010111101011010011100 8
19
bx1010101110001011110101101001110010101011100010111101011010011011101010111000101111010110100110101010101110001011110101101001100110101011100010111101011010011000101010111000101111010110100101111010101110001011110101101001011010101011100010111101011010010101xxxxxxxxxxxxxxxxxxxxxxxxxxxxxxxxxxxxxxxxxxxxxxxxxxxxxxxxxxxxxxxxxxxxxxxxxxxxxxxxxxxxxxxxxxxxxxxx .
bx11111111xxx 1
b111 (
b10101011100010111101011010011100 %
b10101011100010111101011010011100 +
b1010 '
b1010 ,
1&
#80
b101010111000101111010110100111011010101110001011110101101001110010101011100010111101011010011011101010111000101111010110100110101010101110001011110101101001100110101011100010111101011010011000101010111000101111010110100101111010101110001011110101101001011010101011100010111101011010010101000000000000000000000000000000000000000000000000000000000000000000000000000000000000000000000000 -
b10101011100010111101011010011101 =
b10101011100010111101011010011101 ;
1<
bx101010111000101111010110100111011010101110001011110101101001110010101011100010111101011010011011101010111000101111010110100110101010101110001011110101101001100110101011100010111101011010011000101010111000101111010110100101111010101110001011110101101001011010101011100010111101011010010101xxxxxxxxxxxxxxxxxxxxxxxxxxxxxxxxxxxxxxxxxxxxxxxxxxxxxxxxxxxxxxxxxxxxxxxxxxxxxxxxxxxxxxxxxxxxxxxx .
bx111111111xxx 1
b1000 (
b10101011100010111101011010011101 %
b10101011100010111101011010011101 +
b1011 '
b1011 ,
1&
#90
b10101011100010111101011010011110101010111000101111010110100111011010101110001011110101101001110010101011100010111101011010011011101010111000101111010110100110101010101110001011110101101001100110101011100010111101011010011000101010111000101111010110100101111010101110001011110101101001011010101011100010111101011010010101000000000000000000000000000000000000000000000000000000000000000000000000000000000000000000000000 -
b10101011100010111101011010011110 @
b10101011100010111101011010011110 >
1?
bx10101011100010111101011010011110101010111000101111010110100111011010101110001011110101101001110010101011100010111101011010011011101010111000101111010110100110101010101110001011110101101001100110101011100010111101011010011000101010111000101111010110100101111010101110001011110101101001011010101011100010111101011010010101xxxxxxxxxxxxxxxxxxxxxxxxxxxxxxxxxxxxxxxxxxxxxxxxxxxxxxxxxxxxxxxxxxxxxxxxxxxxxxxxxxxxxxxxxxxxxxxx .
bx1111111111xxx 1
b1001 (
b10101011100010111101011010011110 %
b10101011100010111101011010011110 +
b1100 '
b1100 ,
1&
#100
b1010101110001011110101101001111110101011100010111101011010011110101010111000101111010110100111011010101110001011110101101001110010101011100010111101011010011011101010111000101111010110100110101010101110001011110101101001100110101011100010111101011010011000101010111000101111010110100101111010101110001011110101101001011010101011100010111101011010010101000000000000000000000000000000000000000000000000000000000000000000000000000000000000000000000000 -
b10101011100010111101011010011111 C
b10101011100010111101011010011111 A
1B
bx1010101110001011110101101001111110101011100010111101011010011110101010111000101111010110100111011010101110001011110101101001110010101011100010111101011010011011101010111000101111010110100110101010101110001011110101101001100110101011100010111101011010011000101010111000101111010110100101111010101110001011110101101001011010101011100010111101011010010101xxxxxxxxxxxxxxxxxxxxxxxxxxxxxxxxxxxxxxxxxxxxxxxxxxxxxxxxxxxxxxxxxxxxxxxxxxxxxxxxxxxxxxxxxxxxxxxx .
bx11111111111xxx 1
b1010 (
b10101011100010111101011010011111 %
b10101011100010111101011010011111 +
b1101 '
b1101 ,
1&
#110
b101010111000101111010110101000001010101110001011110101101001111110101011100010111101011010011110101010111000101111010110100111011010101110001011110101101001110010101011100010111101011010011011101010111000101111010110100110101010101110001011110101101001100110101011100010111101011010011000101010111000101111010110100101111010101110001011110101101001011010101011100010111101011010010101000000000000000000000000000000000000000000000000000000000000000000000000000000000000000000000000 -
b10101011100010111101011010100000 F
b10101011100010111101011010100000 D
1E
bx101010111000101111010110101000001010101110001011110101101001111110101011100010111101011010011110101010111000101111010110100111011010101110001011110101101001110010101011100010111101011010011011101010111000101111010110100110101010101110001011110101101001100110101011100010111101011010011000101010111000101111010110100101111010101110001011110101101001011010101011100010111101011010010101xxxxxxxxxxxxxxxxxxxxxxxxxxxxxxxxxxxxxxxxxxxxxxxxxxxxxxxxxxxxxxxxxxxxxxxxxxxxxxxxxxxxxxxxxxxxxxxx .
bx111111111111xxx 1
b1011 (
b10101011100010111101011010100000 %
b10101011100010111101011010100000 +
b1110 '
b1110 ,
1&
#120
b10101011100010111101011010100001101010111000101111010110101000001010101110001011110101101001111110101011100010111101011010011110101010111000101111010110100111011010101110001011110101101001110010101011100010111101011010011011101010111000101111010110100110101010101110001011110101101001100110101011100010111101011010011000101010111000101111010110100101111010101110001011110101101001011010101011100010111101011010010101000000000000000000000000000000000000000000000000000000000000000000000000000000000000000000000000 -
b10101011100010111101011010100001 I
b10101011100010111101011010100001 G
1H
bx10101011100010111101011010100001101010111000101111010110101000001010101110001011110101101001111110101011100010111101011010011110101010111000101111010110100111011010101110001011110101101001110010101011100010111101011010011011101010111000101111010110100110101010101110001011110101101001100110101011100010111101011010011000101010111000101111010110100101111010101110001011110101101001011010101011100010111101011010010101xxxxxxxxxxxxxxxxxxxxxxxxxxxxxxxxxxxxxxxxxxxxxxxxxxxxxxxxxxxxxxxxxxxxxxxxxxxxxxxxxxxxxxxxxxxxxxxx .
bx1111111111111xxx 1
b1100 (
b10101011100010111101011010100001 %
b10101011100010111101011010100001 +
b1111 '
b1111 ,
1&
#130
b1010101110001011110101101010001010101011100010111101011010100001101010111000101111010110101000001010101110001011110101101001111110101011100010111101011010011110101010111000101111010110100111011010101110001011110101101001110010101011100010111101011010011011101010111000101111010110100110101010101110001011110101101001100110101011100010111101011010011000101010111000101111010110100101111010101110001011110101101001011010101011100010111101011010010101000000000000000000000000000000000000000000000000000000000000000000000000000000000000000000000000 -
b10101011100010111101011010100010 L
b10101011100010111101011010100010 J
1K
bx1010101110001011110101101010001010101011100010111101011010100001101010111000101111010110101000001010101110001011110101101001111110101011100010111101011010011110101010111000101111010110100111011010101110001011110101101001110010101011100010111101011010011011101010111000101111010110100110101010101110001011110101101001100110101011100010111101011010011000101010111000101111010110100101111010101110001011110101101001011010101011100010111101011010010101xxxxxxxxxxxxxxxxxxxxxxxxxxxxxxxxxxxxxxxxxxxxxxxxxxxxxxxxxxxxxxxxxxxxxxxxxxxxxxxxxxxxxxxxxxxxxxxx .
bx11111111111111xxx 1
b1101 (
b10101011100010111101011010100010 %
b10101011100010111101011010100010 +
b10000 '
b10000 ,
1&
#140
b101010111000101111010110101000111010101110001011110101101010001010101011100010111101011010100001101010111000101111010110101000001010101110001011110101101001111110101011100010111101011010011110101010111000101111010110100111011010101110001011110101101001110010101011100010111101011010011011101010111000101111010110100110101010101110001011110101101001100110101011100010111101011010011000101010111000101111010110100101111010101110001011110101101001011010101011100010111101011010010101000000000000000000000000000000000000000000000000000000000000000000000000000000000000000000000000 -
b10101011100010111101011010100011 O
b10101011100010111101011010100011 M
1N
bx101010111000101111010110101000111010101110001011110101101010001010101011100010111101011010100001101010111000101111010110101000001010101110001011110101101001111110101011100010111101011010011110101010111000101111010110100111011010101110001011110101101001110010101011100010111101011010011011101010111000101111010110100110101010101110001011110101101001100110101011100010111101011010011000101010111000101111010110100101111010101110001011110101101001011010101011100010111101011010010101xxxxxxxxxxxxxxxxxxxxxxxxxxxxxxxxxxxxxxxxxxxxxxxxxxxxxxxxxxxxxxxxxxxxxxxxxxxxxxxxxxxxxxxxxxxxxxxx .
bx111111111111111xxx 1
b1110 (
b10101011100010111101011010100011 %
b10101011100010111101011010100011 +
b10001 '
b10001 ,
1&
#150
b10101011100010111101011010100100101010111000101111010110101000111010101110001011110101101010001010101011100010111101011010100001101010111000101111010110101000001010101110001011110101101001111110101011100010111101011010011110101010111000101111010110100111011010101110001011110101101001110010101011100010111101011010011011101010111000101111010110100110101010101110001011110101101001100110101011100010111101011010011000101010111000101111010110100101111010101110001011110101101001011010101011100010111101011010010101000000000000000000000000000000000000000000000000000000000000000000000000000000000000000000000000 -
b10101011100010111101011010100100 R
b10101011100010111101011010100100 P
1Q
bx10101011100010111101011010100100101010111000101111010110101000111010101110001011110101101010001010101011100010111101011010100001101010111000101111010110101000001010101110001011110101101001111110101011100010111101011010011110101010111000101111010110100111011010101110001011110101101001110010101011100010111101011010011011101010111000101111010110100110101010101110001011110101101001100110101011100010111101011010011000101010111000101111010110100101111010101110001011110101101001011010101011100010111101011010010101xxxxxxxxxxxxxxxxxxxxxxxxxxxxxxxxxxxxxxxxxxxxxxxxxxxxxxxxxxxxxxxxxxxxxxxxxxxxxxxxxxxxxxxxxxxxxxxx .
bx1111111111111111xxx 1
b1111 (
b10101011100010111101011010100100 %
b10101011100010111101011010100100 +
b10010 '
b10010 ,
1&
#160
b1010101110001011110101101010010110101011100010111101011010100100101010111000101111010110101000111010101110001011110101101010001010101011100010111101011010100001101010111000101111010110101000001010101110001011110101101001111110101011100010111101011010011110101010111000101111010110100111011010101110001011110101101001110010101011100010111101011010011011101010111000101111010110100110101010101110001011110101101001100110101011100010111101011010011000101010111000101111010110100101111010101110001011110101101001011010101011100010111101011010010101000000000000000000000000000000000000000000000000000000000000000000000000000000000000000000000000 -
b10101011100010111101011010100101 U
b10101011100010111101011010100101 S
1T
bx1010101110001011110101101010010110101011100010111101011010100100101010111000101111010110101000111010101110001011110101101010001010101011100010111101011010100001101010111000101111010110101000001010101110001011110101101001111110101011100010111101011010011110101010111000101111010110100111011010101110001011110101101001110010101011100010111101011010011011101010111000101111010110100110101010101110001011110101101001100110101011100010111101011010011000101010111000101111010110100101111010101110001011110101101001011010101011100010111101011010010101xxxxxxxxxxxxxxxxxxxxxxxxxxxxxxxxxxxxxxxxxxxxxxxxxxxxxxxxxxxxxxxxxxxxxxxxxxxxxxxxxxxxxxxxxxxxxxxx .
bx11111111111111111xxx 1
b10000 (
b10101011100010111101011010100101 %
b10101011100010111101011010100101 +
b10011 '
b10011 ,
1&
#170
b101010111000101111010110101001101010101110001011110101101010010110101011100010111101011010100100101010111000101111010110101000111010101110001011110101101010001010101011100010111101011010100001101010111000101111010110101000001010101110001011110101101001111110101011100010111101011010011110101010111000101111010110100111011010101110001011110101101001110010101011100010111101011010011011101010111000101111010110100110101010101110001011110101101001100110101011100010111101011010011000101010111000101111010110100101111010101110001011110101101001011010101011100010111101011010010101000000000000000000000000000000000000000000000000000000000000000000000000000000000000000000000000 -
b10101011100010111101011010100110 [
b10101011100010111101011010100110 Y
1Z
bx101010111000101111010110101001101010101110001011110101101010010110101011100010111101011010100100101010111000101111010110101000111010101110001011110101101010001010101011100010111101011010100001101010111000101111010110101000001010101110001011110101101001111110101011100010111101011010011110101010111000101111010110100111011010101110001011110101101001110010101011100010111101011010011011101010111000101111010110100110101010101110001011110101101001100110101011100010111101011010011000101010111000101111010110100101111010101110001011110101101001011010101011100010111101011010010101xxxxxxxxxxxxxxxxxxxxxxxxxxxxxxxxxxxxxxxxxxxxxxxxxxxxxxxxxxxxxxxxxxxxxxxxxxxxxxxxxxxxxxxxxxxxxxxx .
bx111111111111111111xxx 1
b10001 (
b10101011100010111101011010100110 %
b10101011100010111101011010100110 +
b10100 '
b10100 ,
1&
#180
b10101011100010111101011010100111101010111000101111010110101001101010101110001011110101101010010110101011100010111101011010100100101010111000101111010110101000111010101110001011110101101010001010101011100010111101011010100001101010111000101111010110101000001010101110001011110101101001111110101011100010111101011010011110101010111000101111010110100111011010101110001011110101101001110010101011100010111101011010011011101010111000101111010110100110101010101110001011110101101001100110101011100010111101011010011000101010111000101111010110100101111010101110001011110101101001011010101011100010111101011010010101000000000000000000000000000000000000000000000000000000000000000000000000000000000000000000000000 -
b10101011100010111101011010100111 ^
b10101011100010111101011010100111 \
1]
bx10101011100010111101011010100111101010111000101111010110101001101010101110001011110101101010010110101011100010111101011010100100101010111000101111010110101000111010101110001011110101101010001010101011100010111101011010100001101010111000101111010110101000001010101110001011110101101001111110101011100010111101011010011110101010111000101111010110100111011010101110001011110101101001110010101011100010111101011010011011101010111000101111010110100110101010101110001011110101101001100110101011100010111101011010011000101010111000101111010110100101111010101110001011110101101001011010101011100010111101011010010101xxxxxxxxxxxxxxxxxxxxxxxxxxxxxxxxxxxxxxxxxxxxxxxxxxxxxxxxxxxxxxxxxxxxxxxxxxxxxxxxxxxxxxxxxxxxxxxx .
bx1111111111111111111xxx 1
b10010 (
b10101011100010111101011010100111 %
b10101011100010111101011010100111 +
b10101 '
b10101 ,
1&
#190
b1010101110001011110101101010100010101011100010111101011010100111101010111000101111010110101001101010101110001011110101101010010110101011100010111101011010100100101010111000101111010110101000111010101110001011110101101010001010101011100010111101011010100001101010111000101111010110101000001010101110001011110101101001111110101011100010111101011010011110101010111000101111010110100111011010101110001011110101101001110010101011100010111101011010011011101010111000101111010110100110101010101110001011110101101001100110101011100010111101011010011000101010111000101111010110100101111010101110001011110101101001011010101011100010111101011010010101000000000000000000000000000000000000000000000000000000000000000000000000000000000000000000000000 -
b10101011100010111101011010101000 a
b10101011100010111101011010101000 _
1`
bx1010101110001011110101101010100010101011100010111101011010100111101010111000101111010110101001101010101110001011110101101010010110101011100010111101011010100100101010111000101111010110101000111010101110001011110101101010001010101011100010111101011010100001101010111000101111010110101000001010101110001011110101101001111110101011100010111101011010011110101010111000101111010110100111011010101110001011110101101001110010101011100010111101011010011011101010111000101111010110100110101010101110001011110101101001100110101011100010111101011010011000101010111000101111010110100101111010101110001011110101101001011010101011100010111101011010010101xxxxxxxxxxxxxxxxxxxxxxxxxxxxxxxxxxxxxxxxxxxxxxxxxxxxxxxxxxxxxxxxxxxxxxxxxxxxxxxxxxxxxxxxxxxxxxxx .
bx11111111111111111111xxx 1
b10011 (
b10101011100010111101011010101000 %
b10101011100010111101011010101000 +
b10110 '
b10110 ,
1&
