Assignment-1/A7/Reg32b.v
/*
	K Rahul Reddy	17CO119
	Sushruth V	17CO148
	15 October 2018
*/

module Reg32b (output [0:31] data_out, input [0:31] data_in, input clk, input res);
	// 32 one-bit Memory elements with common Clock and Reset signals
	Dff inst1 (data_out[0], data_in[0], clk, res);
	Dff inst2 (data_out[1], data_in[1], clk, res);
	Dff inst3 (data_out[2], data_in[2], clk, res);
	Dff inst4 (data_out[3], data_in[3], clk, res);
	Dff inst5 (data_out[4], data_in[4], clk, res);
	Dff inst6 (data_out[5], data_in[5], clk, res);
	Dff inst7 (data_out[6], data_in[6], clk, res);
	Dff inst8 (data_out[7], data_in[7], clk, res);
	Dff inst9 (data_out[8], data_in[8], clk, res);
	Dff inst10 (data_out[9], data_in[9], clk, res);
	Dff inst11 (data_out[10], data_in[10], clk, res);
	Dff inst12 (data_out[11], data_in[11], clk, res);
	Dff inst13 (data_out[12], data_in[12], clk, res);
	Dff inst14 (data_out[13], data_in[13], clk, res);
	Dff inst15 (data_out[14], data_in[14], clk, res);
	Dff inst16 (data_out[15], data_in[15], clk, res);
	Dff inst17 (data_out[16], data_in[16], clk, res);
	Dff inst18 (data_out[17], data_in[17], clk, res);
	Dff inst19 (data_out[18], data_in[18], clk, res);
	Dff inst20 (data_out[19], data_in[19], clk, res);
	Dff inst21 (data_out[20], data_in[20], clk, res);
	Dff inst22 (data_out[21], data_in[21], clk, res);
	Dff inst23 (data_out[22], data_in[22], clk, res);
	Dff inst24 (data_out[23], data_in[23], clk, res);
	Dff inst25 (data_out[24], data_in[24], clk, res);
	Dff inst26 (data_out[25], data_in[25], clk, res);
	Dff inst27 (data_out[26], data_in[26], clk, res);
	Dff inst28 (data_out[27], data_in[27], clk, res);
	Dff inst29 (data_out[28], data_in[28], clk, res);
	Dff inst30 (data_out[29], data_in[29], clk, res);
	Dff inst31 (data_out[30], data_in[30], clk, res);
	Dff inst32 (data_out[31], data_in[31], clk, res);
endmodule


module Dff (output reg q, input d, input clk, input res);	// 1-bit Memory
	always @ (posedge clk) begin
		if(res == 1'b0) 
			q <= 1'b0;
		else	
			q <= d;
	end
endmodule

Assignment-1/A7/tb_Reg32b.v
/*
	K Rahul Reddy	17CO119
	Sushruth V	17CO148
	15 October 2018
*/

`include "Reg32b.v"

module t_Reg32b;
	initial begin
		$dumpfile("Reg32b.vcd");
		$dumpvars(0, t_Reg32b);
	end
	wire [0:31] data_out;		// outputs 
	reg [0:31] data_in;		// inputs 
	reg clk;			// clock
	reg res;			// reset
	Reg32b inst (data_out, data_in, clk, res);	// 32 bit Register instantiated
	integer i;
	// check for various input combinations
	initial begin
		data_in = 32'b0000000000000000000000000000111;
		clk = 1'b0;
		res = 1'b1;
			
		for (i = 1; i <= 20; i = i + 1) begin
    		#6 data_in = data_in + 1'b1;
   		end
			
	end	

	// tweaking reset bit signal
	initial begin
		#10 res = 1'b1;
		#24 res = 1'b0;
		#10 res = 1'b1;
	end
	

	initial begin
		repeat (30) begin	//Clock signal
			#5 clk = ~ clk;
		end
	end
	
	initial begin	// print result
		$monitor("%3t : data in : %b clk : %b reset : %b \t\t\t data out : %b \n", $time, data_in, clk, res, data_out);	
	end
	
	
endmodule

Assignment-1/A7/Reg32b.vcd
$date
	Mon Oct 15 23:59:56 2018
$end
$version
	Icarus Verilog
$end
$timescale
	1s
$end
$scope module t_Reg32b $end
$var wire 32 ! data_out [0:31] $end
$var reg 1 " clk $end
$var reg 32 # data_in [0:31] $end
$var reg 1 $ res $end
$var integer 32 % i [31:0] $end
$scope module inst $end
$var wire 1 " clk $end
$var wire 32 & data_in [0:31] $end
$var wire 1 $ res $end
$var wire 32 ' data_out [0:31] $end
$scope module inst1 $end
$var wire 1 " clk $end
$var wire 1 ( d $end
$var wire 1 $ res $end
$var reg 1 ) q $end
$upscope $end
$scope module inst10 $end
$var wire 1 " clk $end
$var wire 1 * d $end
$var wire 1 $ res $end
$var reg 1 + q $end
$upscope $end
$scope module inst11 $end
$var wire 1 " clk $end
$var wire 1 , d $end
$var wire 1 $ res $end
$var reg 1 - q $end
$upscope $end
$scope module inst12 $end
$var wire 1 " clk $end
$var wire 1 . d $end
$var wire 1 $ res $end
$var reg 1 / q $end
$upscope $end
$scope module inst13 $end
$var wire 1 " clk $end
$var wire 1 0 d $end
$var wire 1 $ res $end
$var reg 1 1 q $end
$upscope $end
$scope module inst14 $end
$var wire 1 " clk $end
$var wire 1 2 d $end
$var wire 1 $ res $end
$var reg 1 3 q $end
$upscope $end
$scope module inst15 $end
$var wire 1 " clk $end
$var wire 1 4 d $end
$var wire 1 $ res $end
$var reg 1 5 q $end
$upscope $end
$scope module inst16 $end
$var wire 1 " clk $end
$var wire 1 6 d $end
$var wire 1 $ res $end
$var reg 1 7 q $end
$upscope $end
$scope module inst17 $end
$var wire 1 " clk $end
$var wire 1 8 d $end
$var wire 1 $ res $end
$var reg 1 9 q $end
$upscope $end
$scope module inst18 $end
$var wire 1 " clk $end
$var wire 1 : d $end
$var wire 1 $ res $end
$var reg 1 ; q $end
$upscope $end
$scope module inst19 $end
$var wire 1 " clk $end
$var wire 1 < d $end
$var wire 1 $ res $end
$var reg 1 = q $end
$upscope $end
$scope module inst2 $end
$var wire 1 " clk $end
$var wire 1 > d $end
$var wire 1 $ res $end
$var reg 1 ? q $end
$upscope $end
$scope module inst20 $end
$var wire 1 " clk $end
$var wire 1 @ d $end
$var wire 1 $ res $end
$var reg 1 A q $end
$upscope $end
$scope module inst21 $end
$var wire 1 " clk $end
$var wire 1 B d $end
$var wire 1 $ res $end
$var reg 1 C q $end
$upscope $end
$scope module inst22 $end
$var wire 1 " clk $end
$var wire 1 D d $end
$var wire 1 $ res $end
$var reg 1 E q $end
$upscope $end
$scope module inst23 $end
$var wire 1 " clk $end
$var wire 1 F d $end
$var wire 1 $ res $end
$var reg 1 G q $end
$upscope $end
$scope module inst24 $end
$var wire 1 " clk $end
$var wire 1 H d $end
$var wire 1 $ res $end
$var reg 1 I q $end
$upscope $end
$scope module inst25 $end
$var wire 1 " clk $end
$var wire 1 J d $end
$var wire 1 $ res $end
$var reg 1 K q $end
$upscope $end
$scope module inst26 $end
$var wire 1 " clk $end
$var wire 1 L d $end
$var wire 1 $ res $end
$var reg 1 M q $end
$upscope $end
$scope module inst27 $end
$var wire 1 " clk $end
$var wire 1 N d $end
$var wire 1 $ res $end
$var reg 1 O q $end
$upscope $end
$scope module inst28 $end
$var wire 1 " clk $end
$var wire 1 P d $end
$var wire 1 $ res $end
$var reg 1 Q q $end
$upscope $end
$scope module inst29 $end
$var wire 1 " clk $end
$var wire 1 R d $end
$var wire 1 $ res $end
$var reg 1 S q $end
$upscope $end
$scope module inst3 $end
$var wire 1 " clk $end
$var wire 1 T d $end
$var wire 1 $ res $end
$var reg 1 U q $end
$upscope $end
$scope module inst30 $end
$var wire 1 " clk $end
$var wire 1 V d $end
$var wire 1 $ res $end
$var reg 1 W q $end
$upscope $end
$scope module inst31 $end
$var wire 1 " clk $end
$var wire 1 X d $end
$var wire 1 $ res $end
$var reg 1 Y q $end
$upscope $end
$scope module inst32 $end
$var wire 1 " clk $end
$var wire 1 Z d $end
$var wire 1 $ res $end
$var reg 1 [ q $end
$upscope $end
$scope module inst4 $end
$var wire 1 " clk $end
$var wire 1 \ d $end
$var wire 1 $ res $end
$var reg 1 ] q $end
$upscope $end
$scope module inst5 $end
$var wire 1 " clk $end
$var wire 1 ^ d $end
$var wire 1 $ res $end
$var reg 1 _ q $end
$upscope $end
$scope module inst6 $end
$var wire 1 " clk $end
$var wire 1 ` d $end
$var wire 1 $ res $end
$var reg 1 a q $end
$upscope $end
$scope module inst7 $end
$var wire 1 " clk $end
$var wire 1 b d $end
$var wire 1 $ res $end
$var reg 1 c q $end
$upscope $end
$scope module inst8 $end
$var wire 1 " clk $end
$var wire 1 d d $end
$var wire 1 $ res $end
$var reg 1 e q $end
$upscope $end
$scope module inst9 $end
$var wire 1 " clk $end
$var wire 1 f d $end
$var wire 1 $ res $end
$var reg 1 g q $end
$upscope $end
$upscope $end
$upscope $end
$enddefinitions $end
#0
$dumpvars
xg
0f
xe
0d
xc
0b
xa
0`
x_
0^
x]
0\
x[
1Z
xY
1X
xW
1V
xU
0T
xS
0R
xQ
0P
xO
0N
xM
0L
xK
0J
xI
0H
xG
0F
xE
0D
xC
0B
xA
0@
x?
0>
x=
0<
x;
0:
x9
08
x7
06
x5
04
x3
02
x1
00
x/
0.
x-
0,
x+
0*
x)
0(
bx '
b111 &
b1 %
1$
b111 #
0"
bx !
$end
#5
0)
0?
0U
0]
0_
0a
0c
0e
0g
0+
0-
0/
01
03
05
07
09
0;
0=
0A
0C
0E
0G
0I
0K
0M
0O
0Q
0S
1W
1Y
b111 !
b111 '
1[
1"
#6
1R
0V
0X
0Z
b10 %
b1000 #
b1000 &
#10
0"
#12
1Z
b11 %
b1001 #
b1001 &
#15
0Y
0W
b1001 !
b1001 '
1S
1"
#18
1X
0Z
b100 %
b1010 #
b1010 &
#20
0"
#24
1Z
b101 %
b1011 #
b1011 &
#25
b1011 !
b1011 '
1Y
1"
#30
1V
0X
0Z
0"
b110 %
b1100 #
b1100 &
#34
0$
#35
0[
0Y
b0 !
b0 '
0S
1"
#36
1Z
b111 %
b1101 #
b1101 &
#40
0"
#42
1X
0Z
b1000 %
b1110 #
b1110 &
#44
1$
#45
1S
1W
b1110 !
b1110 '
1Y
1"
#48
1Z
b1001 %
b1111 #
b1111 &
#50
0"
#54
1P
0R
0V
0X
0Z
b1010 %
b10000 #
b10000 &
#55
0Y
0W
0S
b10000 !
b10000 '
1Q
1"
#60
1Z
0"
b1011 %
b10001 #
b10001 &
#65
b10001 !
b10001 '
1[
1"
#66
1X
0Z
b1100 %
b10010 #
b10010 &
#70
0"
#72
1Z
b1101 %
b10011 #
b10011 &
#75
b10011 !
b10011 '
1Y
1"
#78
1V
0X
0Z
b1110 %
b10100 #
b10100 &
#80
0"
#84
1Z
b1111 %
b10101 #
b10101 &
#85
1W
b10101 !
b10101 '
0Y
1"
#90
1X
0Z
0"
b10000 %
b10110 #
b10110 &
#95
0[
b10110 !
b10110 '
1Y
1"
#96
1Z
b10001 %
b10111 #
b10111 &
#100
0"
#102
1R
0V
0X
0Z
b10010 %
b11000 #
b11000 &
#105
1S
0W
b11000 !
b11000 '
0Y
1"
#108
1Z
b10011 %
b11001 #
b11001 &
#110
0"
#114
1X
0Z
b10100 %
b11010 #
b11010 &
#115
b11010 !
b11010 '
1Y
1"
#120
1Z
0"
b10101 %
b11011 #
b11011 &
#125
b11011 !
b11011 '
1[
1"
