Assignment-2/A3/CU.v
/*
        K Rahul Reddy	17CO119
        Sushruth V	17CO148
        24 October 2018

        funct7[5] and funct3[2:0] are required to identify operation.
*/
module CU(output [3:0] Op, input[1:0] ALU_Op, input[6:0] funct7, input[2:0] funct3);
    wire F0 = funct3[0];
    wire F1 = funct3[1];
    wire F2 = funct3[2];
    wire F3 = funct7[5]; 
    assign Op[3] = 0;
    assign Op[2] = ALU_Op[0] | (ALU_Op[1] & F3 & ~F2 & ~F1 & ~F0);
    assign Op[1] = ~F1 | ~ALU_Op[1];
    assign Op[0] = ALU_Op[1] & F1 & ~F0;
endmodule

Assignment-2/A3/tb_CU.v
/*
	K Rahul Reddy	17CO119
	Sushruth V	17CO148
	24 October 2018
*/
`include "CU.v"

module tb_CU;
    initial begin
        $dumpfile("CU.vcd");
        $dumpvars(0, tb_CU);
    end
    reg[1:0] ALU_Op;
    reg[6:0] funct7;
    reg[2:0] funct3;
    wire[3:0] Op;
    integer i;
    CU inst(Op, ALU_Op, funct7, funct3);
    initial begin
    #20   ALU_Op = 2'b00;
        funct7 = 7'b0100111;
        funct3 = 3'b111;
        $display("Case 0: Add(ALU_Op code)");
    #20    ALU_Op = 2'b01;
        funct7 = 7'b0000000;
        funct3 = 3'b111;
        $display("Case 1: Subtract(ALU_Op code)");
    #20 ALU_Op = 2'b10;
        funct7 = 7'b0000000;
        funct3 = 3'b000;
        $display("Case 2: Add(R-type)");
    #20 ALU_Op = 2'b10;
        funct7 = 7'b0100000;
        funct3 = 3'b000;
        $display("Case 3: Subtract(R-type)");
    #20 ALU_Op = 2'b10;
        funct7 = 7'b0000000;
        funct3 = 3'b111;
        $display("Case 4: And(R-type)");
    #20 ALU_Op = 2'b10;
        funct7 = 7'b0000000;
        funct3 = 3'b110;
        $display("Case 5: Or(R-type)");
    #20;
    end
    initial begin
        for(i = 0; i < 6; i++)
    #21    $display("ALU_Op = %3b\t\tfunct7 = %8b\t\tfunct3 = %4b\n\nOpcode = %b\n", ALU_Op, funct7, funct3, Op);
    end
endmodule

Assignment-2/A3/CU.vcd
$date
	Thu Oct 25 18:39:34 2018
$end
$version
	Icarus Verilog
$end
$timescale
	1s
$end
$scope module tb_CU $end
$var wire 4 ! Op [3:0] $end
$var reg 2 " ALU_Op [1:0] $end
$var reg 3 # funct3 [2:0] $end
$var reg 7 $ funct7 [6:0] $end
$var integer 32 % i [31:0] $end
$scope module inst $end
$var wire 2 & ALU_Op [1:0] $end
$var wire 3 ' funct3 [2:0] $end
$var wire 7 ( funct7 [6:0] $end
$var wire 4 ) Op [3:0] $end
$var wire 1 * F3 $end
$var wire 1 + F2 $end
$var wire 1 , F1 $end
$var wire 1 - F0 $end
$upscope $end
$upscope $end
$enddefinitions $end
#0
$dumpvars
x-
x,
x+
x*
b0xxx )
bx (
bx '
bx &
b0 %
bx $
bx #
bx "
b0xxx !
$end
#20
b10 !
b10 )
1-
1,
1+
1*
b111 #
b111 '
b100111 $
b100111 (
b0 "
b0 &
#21
b1 %
#40
b110 !
b110 )
0*
b0 $
b0 (
b1 "
b1 &
#42
b10 %
#60
b10 !
b10 )
0-
0,
0+
b0 #
b0 '
b10 "
b10 &
#63
b11 %
#80
b110 !
b110 )
1*
b100000 $
b100000 (
#84
b100 %
#100
b0 !
b0 )
1-
1,
1+
0*
b111 #
b111 '
b0 $
b0 (
#105
b101 %
#120
b1 !
b1 )
0-
b110 #
b110 '
#126
b110 %
