Assignment-1/A3/halfAdder.v
/*
	K Rahul Reddy	17CO119
	Sushruth V	17CO148
	15 October 2018
*/


module halfAdder (output reg sum, output reg carry, input op1, input op2);
	always @ (op1 or op2) begin		//if inputs are 0 and 0, thread is not executed
		sum = op1 ^ op2;		// sum bit of two operands
		carry = op1 & op2;		// carry bit of two operands
	end
endmodule

Assignment-1/A3/tb_halfAdder.v
/*
	K Rahul Reddy	17CO119
	Sushruth V	17CO148
	15 October 2018
*/
`include "halfAdder.v"

module main;
	initial begin
		$dumpfile("tb_halfAdder.vcd");	
		$dumpvars(0, main);
	end
	wire sum, carry;		//outputs
	reg op1,op2;			//inputs 	
	reg[3:0] n1;
	reg[3:0] n2;
	integer i;
	halfAdder inst (sum, carry, op1, op2);		//instantiating half adder
	initial begin
		n1 = 3;
		n2 = 5;
        	op1 = 1'b0;
        	op2 = 1'b0;
        	for (i = 0;i <= 3;i = i + 1) begin
        	#1	$display("Sum of %d and %d", n1[i], n2[i]);
		#1	op1=n1[i];	//input fields		
			op2=n2[i];

	    	#1	$display("Sum = %d\nCarry = %d\n", sum, carry);	// Displaying the sum and carry bits	
        end	
    end
endmodule

Assignment-1/A3/tb_halfAdder.vcd
$date
	Mon Oct 15 21:32:03 2018
$end
$version
	Icarus Verilog
$end
$timescale
	1s
$end
$scope module main $end
$var wire 1 ! sum $end
$var wire 1 " carry $end
$var reg 4 # n1 [3:0] $end
$var reg 4 $ n2 [3:0] $end
$var reg 1 % op1 $end
$var reg 1 & op2 $end
$var integer 32 ' i [31:0] $end
$scope module inst $end
$var wire 1 % op1 $end
$var wire 1 & op2 $end
$var reg 1 " carry $end
$var reg 1 ! sum $end
$upscope $end
$upscope $end
$enddefinitions $end
#0
$dumpvars
b0 '
0&
0%
b101 $
b11 #
0"
0!
$end
#2
1"
1&
1%
#3
b1 '
#5
0"
1!
0&
#6
b10 '
#8
1&
0%
#9
b11 '
#11
0!
0&
#12
b100 '
