Assignment-1/A2/Decoder/decoder.v
/*
	K Rahul Reddy	17CO119
	Sushruth V	17CO148
	15 October 2018
*/

module decoder (output reg [0:15] out, input [0:3] in);
	always @ (in) begin			//if not used case is read as module	
		case (in)			//switch to match 4-bit input to 16-bit output  		
			4'b0000 : out = 16'b0000000000000001;
			4'b0001 : out = 16'b0000000000000010;
			4'b0010 : out = 16'b0000000000000100;
			4'b0011 : out = 16'b0000000000001000;
			4'b0100 : out = 16'b0000000000010000;
			4'b0101 : out = 16'b0000000000100000;
			4'b0110 : out = 16'b0000000001000000;
			4'b0111 : out = 16'b0000000010000000;
			4'b1000 : out = 16'b0000000100000000;
			4'b1001 : out = 16'b0000001000000000;
			4'b1010 : out = 16'b0000010000000000;
			4'b1011 : out = 16'b0000100000000000;
			4'b1100 : out = 16'b0001000000000000;
			4'b1101 : out = 16'b0010000000000000;
			4'b1110 : out = 16'b0100000000000000;
			4'b1111 : out = 16'b1000000000000000;
			default	: out = 16'b0000000000000000;
		endcase
	end
endmodule

Assignment-1/A2/Decoder/tb_decoder.v
/*
	K Rahul Reddy	17CO119
	Sushruth V	17CO148
	15 October 2018
*/

`include "decoder.v"

module four_16BitDecoder;
	initial begin
		$dumpfile("tb_decoder.vcd");
		$dumpvars(0, four_16BitDecoder);
	end
	wire [0:15] out;		// output is a collection of 15 wires
	reg [0:3] in;			// input is 4-bit register
	decoder inst (out, in);		// instantiating decoder module
	
	initial begin			// check for various input combinations
		in = 4'b0000;
	#10	in = 4'b0001;	
	#10	in = 4'b0010;
	#10	in = 4'b0011;	
	#10	in = 4'b0100;
	#10	in = 4'b0101;	
	#10	in = 4'b0110;
	#10	in = 4'b0111;
	#10	in = 4'b1000;
	#10	in = 4'b1001;	
	#10	in = 4'b1010;
	#10	in = 4'b1011;	
	#10	in = 4'b1100;
	#10	in = 4'b1101;	
	#10	in = 4'b1110;
	#10	in = 4'b1111;	
	#10;					
	end	
	
	initial begin			// print result
		 $monitor("input: %b output: %b", in, out);	
	end
endmodule

Assignment-1/A2/Decoder/tb_decoder.vcd
$date
	Mon Oct 15 20:23:59 2018
$end
$version
	Icarus Verilog
$end
$timescale
	1s
$end
$scope module four_16BitDecoder $end
$var wire 16 ! out [0:15] $end
$var reg 4 " in [0:3] $end
$scope module inst $end
$var wire 4 # in [0:3] $end
$var reg 16 $ out [0:15] $end
$upscope $end
$upscope $end
$enddefinitions $end
#0
$dumpvars
b1 $
b0 #
b0 "
b1 !
$end
#10
b10 !
b10 $
b1 "
b1 #
#20
b100 !
b100 $
b10 "
b10 #
#30
b1000 !
b1000 $
b11 "
b11 #
#40
b10000 !
b10000 $
b100 "
b100 #
#50
b100000 !
b100000 $
b101 "
b101 #
#60
b1000000 !
b1000000 $
b110 "
b110 #
#70
b10000000 !
b10000000 $
b111 "
b111 #
#80
b100000000 !
b100000000 $
b1000 "
b1000 #
#90
b1000000000 !
b1000000000 $
b1001 "
b1001 #
#100
b10000000000 !
b10000000000 $
b1010 "
b1010 #
#110
b100000000000 !
b100000000000 $
b1011 "
b1011 #
#120
b1000000000000 !
b1000000000000 $
b1100 "
b1100 #
#130
b10000000000000 !
b10000000000000 $
b1101 "
b1101 #
#140
b100000000000000 !
b100000000000000 $
b1110 "
b1110 #
#150
b1000000000000000 !
b1000000000000000 $
b1111 "
b1111 #
